tinydb_appengine/__init__.py
tinydb_appengine/storages.py
tinydb_appengine-1.0.6.dist-info/LICENSE
tinydb_appengine-1.0.6.dist-info/METADATA
tinydb_appengine-1.0.6.dist-info/WHEEL
tinydb_appengine-1.0.6.dist-info/top_level.txt
tinydb_appengine-1.0.6.dist-info/RECORD
